scilib/__init__.py
scilib/antv/__init__.py
scilib/antv/sankey.py
scilib/cnki/importer.py
scilib/db/__init__.py
scilib/db/es.py
scilib/db/trans.py
scilib/gender/.Rhistory
scilib/gender/README.md
scilib/gender/__init__.py
scilib/gender/agefromname_pypi/__init__.py
scilib/gender/agefromname_pypi/public.py
scilib/gender/api/__init__.py
scilib/gender/api/index.py
scilib/gender/api_gender/README.md
scilib/gender/api_gender/__init__.py
scilib/gender/api_gender/public.py
scilib/gender/api_genderize/README.md
scilib/gender/api_genderize/__init__.py
scilib/gender/api_genderize/public.py
scilib/gender/api_namsor/README.md
scilib/gender/api_namsor/__init__.py
scilib/gender/api_namsor/public.py
scilib/gender/benchmark/README.md
scilib/gender/benchmark/__init__.py
scilib/gender/benchmark/benchmark.py
scilib/gender/benchmark/results.csv
scilib/gender/chinese_naive_bayes/__init__.py
scilib/gender/chinese_naive_bayes/chinese_gender.py
scilib/gender/gender_computer/README.md
scilib/gender/gender_computer/__init__.py
scilib/gender/gender_computer/public.py
scilib/gender/gender_detector/Gemfile
scilib/gender/gender_detector/Gemfile.lock
scilib/gender/gender_detector/README.md
scilib/gender/gender_detector/cli.rb
scilib/gender/gender_detector/public.py
scilib/gender/gender_guesser_pypi/README.md
scilib/gender/gender_guesser_pypi/__init__.py
scilib/gender/gender_guesser_pypi/public.py
scilib/gender/gender_predictor/README.md
scilib/gender/gender_predictor/USSSALoader.py
scilib/gender/gender_predictor/genderPredictor.py
scilib/gender/gender_predictor/public.py
scilib/gender/gender_r/README.md
scilib/gender/gender_r/gender.R
scilib/gender/gender_r/public.py
scilib/gender/genderizer_pypi/README.md
scilib/gender/genderizer_pypi/__init__.py
scilib/gender/genderizer_pypi/public.py
scilib/gender/go_gender/README.md
scilib/gender/go_gender/classifier.serialized
scilib/gender/go_gender/cli.go
scilib/gender/go_gender/go.mod
scilib/gender/go_gender/go.sum
scilib/gender/go_gender/public.py
scilib-0.0.14.dist-info/entry_points.txt
scilib-0.0.14.dist-info/LICENSE
scilib-0.0.14.dist-info/WHEEL
scilib-0.0.14.dist-info/METADATA
scilib-0.0.14.dist-info/RECORD
